luxonis_train/__init__.py
luxonis_train/__main__.py
luxonis_train/registry.py
luxonis_train/tasks.py
luxonis_train/typing.py
luxonis_train/upgrade.py
luxonis_train/variants.py
luxonis_train/assigners/__init__.py
luxonis_train/assigners/atss_assigner.py
luxonis_train/assigners/tal_assigner.py
luxonis_train/assigners/utils.py
luxonis_train/attached_modules/__init__.py
luxonis_train/attached_modules/base_attached_module.py
luxonis_train/attached_modules/losses/__init__.py
luxonis_train/attached_modules/losses/adaptive_detection_loss.py
luxonis_train/attached_modules/losses/base_loss.py
luxonis_train/attached_modules/losses/bce_with_logits.py
luxonis_train/attached_modules/losses/cross_entropy.py
luxonis_train/attached_modules/losses/ctc_loss.py
luxonis_train/attached_modules/losses/efficient_keypoint_bbox_loss.py
luxonis_train/attached_modules/losses/embedding_losses.py
luxonis_train/attached_modules/losses/fomo_localization_loss.py
luxonis_train/attached_modules/losses/ohem_loss.py
luxonis_train/attached_modules/losses/precision_dfl_detection_loss.py
luxonis_train/attached_modules/losses/precision_dlf_segmentation_loss.py
luxonis_train/attached_modules/losses/reconstruction_segmentation_loss.py
luxonis_train/attached_modules/losses/sigmoid_focal_loss.py
luxonis_train/attached_modules/losses/smooth_bce_with_logits.py
luxonis_train/attached_modules/losses/softmax_focal_loss.py
luxonis_train/attached_modules/metrics/__init__.py
luxonis_train/attached_modules/metrics/base_metric.py
luxonis_train/attached_modules/metrics/dice_coefficient.py
luxonis_train/attached_modules/metrics/embedding_metrics.py
luxonis_train/attached_modules/metrics/mean_iou.py
luxonis_train/attached_modules/metrics/object_keypoint_similarity.py
luxonis_train/attached_modules/metrics/ocr_accuracy.py
luxonis_train/attached_modules/metrics/torchmetrics.py
luxonis_train/attached_modules/metrics/utils.py
luxonis_train/attached_modules/metrics/confusion_matrix/__init__.py
luxonis_train-0.4.1.dist-info/licenses/LICENSE
luxonis_train-0.4.1.dist-info/METADATA
luxonis_train-0.4.1.dist-info/WHEEL
luxonis_train-0.4.1.dist-info/entry_points.txt
luxonis_train-0.4.1.dist-info/top_level.txt
luxonis_train-0.4.1.dist-info/RECORD
