Metadata-Version: 2.4
Name: luxonis-train
Version: 0.4.1
Summary: Luxonis training framework for seamless training of various neural networks.
Author-email: Luxonis <support@luxonis.com>
Maintainer-email: Luxonis <support@luxonis.com>
License:                                  Apache License
Project-URL: repository, https://github.com/luxonis/luxonis-train
Project-URL: issues, https://github.com/luxonis/luxonis-train/issues
Keywords: ml,training,luxonis,oak
Classifier: License :: OSI Approved :: Apache Software License
Classifier: Development Status :: 4 - Beta
Classifier: Programming Language :: Python :: 3.10
Classifier: Programming Language :: Python :: 3.11
Classifier: Programming Language :: Python :: 3.12
Classifier: Topic :: Scientific/Engineering :: Artificial Intelligence
Classifier: Topic :: Scientific/Engineering :: Image Processing
Classifier: Topic :: Scientific/Engineering :: Image Recognition
Requires-Python: >=3.10
License-File: LICENSE
Requires-Dist: blobconverter>=1.4.2
Requires-Dist: lightning>=2.5.0
Requires-Dist: luxonis-ml[data,tracker]>=0.8.1
Requires-Dist: onnx<1.16.2; sys_platform == "win32"
Requires-Dist: onnx>=1.16.2; sys_platform != "win32"
Requires-Dist: onnxruntime>=1.13.1
Requires-Dist: onnxsim>=0.4.10
Requires-Dist: optuna>=3.6.0
Requires-Dist: optuna-integration>=3.6.0
Requires-Dist: parameterized>=0.9.0
Requires-Dist: psycopg2-binary>=2.9.1
Requires-Dist: faster-coco-eval>=1.6.5
Requires-Dist: rich>=13.0.0
Requires-Dist: s3fs>=2023.0.0
Requires-Dist: tensorboard>=2.10.1
Requires-Dist: torchvision>=0.16.0
Requires-Dist: cyclopts>=3.0.0
Requires-Dist: mlflow>=2.10.0
Requires-Dist: psutil>=5.0.0
Requires-Dist: tabulate>=0.9.0
Requires-Dist: grad-cam>=1.5.4
Requires-Dist: pytorch_metric_learning>=2.7.0
Requires-Dist: scikit-learn>=1.5.0
Requires-Dist: seaborn>=0.13.2
Requires-Dist: torchmetrics<=1.6.3
Requires-Dist: semver~=3.0
Requires-Dist: onnxscript>=0.5.6
Requires-Dist: termcolor>=1.1
Requires-Dist: pydantic-extra-types>=2.10.6
Provides-Extra: dev
Requires-Dist: gdown>=4.2.0; extra == "dev"
Requires-Dist: pre-commit<4.0.0,>=3.2.1; extra == "dev"
Requires-Dist: opencv-stubs>=0.0.8; extra == "dev"
Requires-Dist: pytest-cov>=4.1.0; extra == "dev"
Requires-Dist: pytest-subtests>=0.12.1; extra == "dev"
Requires-Dist: pytest-order>=1.3.0; extra == "dev"
Requires-Dist: pytest-timeout>=2.4.0; extra == "dev"
Dynamic: license-file
